LICENSE
MANIFEST.in
README.rst
redisify.py
setup.cfg
setup.py
django_heroku_redisify.egg-info/PKG-INFO
django_heroku_redisify.egg-info/SOURCES.txt
django_heroku_redisify.egg-info/dependency_links.txt
django_heroku_redisify.egg-info/requires.txt
django_heroku_redisify.egg-info/top_level.txt
tests/test_redisify.py