Metadata-Version: 1.1
Name: django-heroku-redisify
Version: 0.2.1
Summary: Friendly Redis for Django on Heroku
Home-page: https://github.com/dirn/django-heroku-redisify
Author: Andy Dirnberger
Author-email: dirn@dirnonline.com
License: Copyright (c) 2013, Andy Dirnberger
